{"symbol": "NRFB","address": "0x00281dFCe4cfD72c0b6FDA2AAaF077258743f9E8","overview":{"en": "NuriFootBall gives a variety of existing service systems. We will provide services for users. Various services are being prepared, including Nurifootball's unique NFT/P2E/Platform/Match prediction service, and some users can enjoy blockchain and daily life through NuriFootball's offline stores"},"email": "","website": "https://www.nurifootball.io/","state": "NORMAL","links": {"blog": "https://blog.naver.com/nurifootball2020","twitter": "https://twitter.com/NuRiFootBall_","telegram": "","github": ""}}