{
	"symbol": "GAI",
	"address": "0x02Fcda86fFFEfC71d83180b436E5d7f78906345C",
	"overview": {
		"en": "We just intrested in blockchain to make this coin for fun.",
		"zh": "丐币（调侃），一群区块链爱好者的内部交流币，不带商业性质。"
	},
	"links": {},
	"email": "hrhsea@gmail.com",
	"website": "http://gai.wulanghai.com/",
	"whitepaper": "http://gai.wulanghai.com/whitepaper.html",
	"published_on": "2018-07-09"
}                                                                                                                                                  
