{
  "symbol": "XEN",
  "address": "0x06450dEe7FD2Fb8E39061434BAbCFC05599a6Fb8",
  "overview":{
        "en": "XEN aims to become a community-building crypto asset that connects like minded people together and provide the lowest barrier to entry through its unique tokenomics.",
        "zh": "XEN 旨在成为一种社区构建型的加密资产，通过其独特的代币经济学，连接志同道合的人，并提供最低的进入门槛。"
  },
  "website": "https://xen.network/",
  "links": {
    "twitter": "https://twitter.com/XEN_Crypto",
    "telegram": "https://t.me/XENCryptoTalk"
  }
}