{"symbol": "erowan","address": "0x07baC35846e5eD502aA91AdF6A9e7aA210F2DcbE","overview":{"en": "SifChain (erowan) is a cryptocurrency and operates on the Ethereum platform. SifChain has a current supply of 0. The last known price of SifChain is 0.95245829 USD and is down -5.72 over the last 24 hours. It is currently trading on 3 active market(s) with $1,955,308.75 traded over the last 24 hours. More information can be found at https://sifchain.finance/."},"email": "","website": "https://sifchain.finance/","state": "NORMAL","links": {"blog": "https://medium.com/sifchain-finance","twitter": "https://twitter.com/sifchain","telegram": "","github": ""}}