{"symbol": "$PIR","address": "0x0e3c91eD7D966fF1F7B58aB739A55E3c4473Cd27","overview":{"en": "PIRANHAS ($PIR) is a cryptocurrency and operates on the Ethereum platform. PIRANHAS has a current supply of 0. The last known price of PIRANHAS is 2.07322563 USD and is down -4.32 over the last 24 hours. It is currently trading on 1 active market(s) with $0.00 traded over the last 24 hours. More information can be found at https://piranhas.finance."},"email": "","website": "https://piranhas.finance","state": "NORMAL","links": {"blog": "https://piranhasfinance.medium.com","twitter": "https://twitter.com/piranhasfinance","telegram": "","github": ""}}