{"symbol": "ROC","address": "0x1BcBc54166F6bA149934870b60506199b6C9dB6D","overview":{"en": "Rasputin Online Coin (ROC) is a cryptocurrency and operates on the Ethereum platform. Rasputin Online Coin has a current supply of 5,000,000 with 1,383,638.01278683 in circulation. The last known price of Rasputin Online Coin is 1.30921745 USD and is up 0.00 over the last 24 hours. More information can be found at https://ico.rasputinonline.com/."},"email": "","website": "https://ico.rasputinonline.com/","state": "NORMAL","links": {"blog": "","twitter": "https://twitter.com/rasputinonline","telegram": "","github": ""}}