{"symbol": "mIAU","address": "0x1d350417d9787E000cc1b95d70E9536DcD91F373","overview":{"en": "Mirrored iShares Gold Trust (mIAU) is a cryptocurrency and operates on the Ethereum platform. Mirrored iShares Gold Trust has a current supply of 1,360,089.066891. The last known price of Mirrored iShares Gold Trust is 17.12211526 USD and is up 0.49 over the last 24 hours. It is currently trading on 2 active market(s) with $74,826.97 traded over the last 24 hours. More information can be found at https://mirror.finance."},"email": "","website": "https://mirror.finance","state": "NORMAL","links": {"blog": "https://medium.com/mirror-protocol/","twitter": "https://twitter.com/mirror_protocol","telegram": "","github": ""}}