{
    "website": "https://trumperc.com/",
    "published_on": "2023-05-02",
    "links": {
        "telegram": "https://t.me/trumptokenerc",
        "twitter": "https://twitter.com/trumptokenerc"
    },
    "overview": {
        "en": "We holds a positive attitude towards the trump token, believing it to be a project with potential.\nAccording to our estimation, the valuation of the project will continue to rise, and they plan to hold a certain amount of tokens. Overall, we holds a positive view on the trump token, considering it a project worth paying attention to."
    },
    "symbol": "Trump",
    "initial_price": {
        "ETH": "0.00000000928 ETH"
    },
    "whitepaper": "https://trumperc.com/",
    "address": "0x34134AB45843B4915c1C28C5F802c375861002Bd"
}