{"symbol": "YUI","address": "0x4c10BD19688B906665fBd53415f279F34b44ECE7","overview":{"en": "YUI Token (YUI) is a cryptocurrency and operates on the Ethereum platform. YUI Token has a current supply of 27,823 with 0 in circulation. The last known price of YUI Token is 27.43098472 USD and is down -5.98 over the last 24 hours. It is currently trading on 1 active market(s) with $86,114.50 traded over the last 24 hours. More information can be found at https://www.yui.finance/."},"email": "","website": "https://www.yui.finance/","state": "NORMAL","links": {"blog": "https://yuifinance.medium.com/","twitter": "https://twitter.com/FinanceYUI","telegram": "","github": ""}}