{
  "symbol": "IFUM",
  "address": "0x5278852029f4fdf91eb2d40614ff49b4b4b7c765",
  "overview":{
        "en": "Brand publishing & marketing agent platform with 8 dapp services developed by ELSOLCOM.",
        "zn": ""
  },
  "email": "support@infleum.io",
  "website": "https://www.infleum.io/",
  "whitepaper": "https://drive.google.com/file/d/1Vi7Eush0SDUQxpyw4fX6IukfIAySTdHb/view",
  "state": "NORMAL",
  "published_on": "2018-12-10",
  "initial_price":{
        "USD": "0.02 USD",
  },
  "links": {
    "blog": "",
    "twitter": "https://twitter.com/infleum",
    "telegram": "https://t.me/infleum_official_EN",
    "github": "https://github.com/infleum",
    "facebook": "https://www.facebook.com/InfleumOfficial",
    "reddit": "https://www.reddit.com/user/infleum/",
    "slack": "",
    "medium": "https://medium.com/infleum"
  }
}
