{"symbol": "yTSLA","address": "0x5322A3556F979cE2180B30e689a9436fDDCB1021","overview":{"en": "yTSLA Finance (yTSLA) is a cryptocurrency and operates on the Ethereum platform. yTSLA Finance has a current supply of 69,590.65623104 with 66,417.79899251 in circulation. The last known price of yTSLA Finance is 1.24290937 USD and is up 35.88 over the last 24 hours. It is currently trading on 3 active market(s) with $23,024.52 traded over the last 24 hours. More information can be found at https://ytsla.finance/."},"email": "","website": "https://ytsla.finance/","state": "NORMAL","links": {"blog": "","twitter": "https://twitter.com/yTSLAFi","telegram": "","github": ""}}