{"symbol": "DFSOCIAL","address": "0x54ee01beB60E745329E6a8711Ad2D6cb213e38d7","overview":{"en": "DeFiSocial Gaming (DFSOCIAL) is a cryptocurrency and operates on the Ethereum platform. DeFiSocial Gaming has a current supply of 0. The last known price of DeFiSocial Gaming is 486.23555403 USD and is down -3.36 over the last 24 hours. It is currently trading on 1 active market(s) with $1,547,629.81 traded over the last 24 hours. More information can be found at https://dfsocial.com/."},"email": "","website": "https://dfsocial.com/","state": "NORMAL","links": {"blog": "https://defisocial.medium.com/","twitter": "https://twitter.com/DFSocial_Gaming","telegram": "","github": ""}}