{
    "website":"https://iotchain.io/",
    "links":{
        "reddit":"https://www.reddit.com/r/itcofficial/",
        "github":"https://github.com/IoTChainCode",
        "slack":"https://iotchaingroup.slack.com/",
        "telegram":"https://t.me/IoTChain",
        "twitter":"https://twitter.com/IoT_Chain",
        "facebook":"https://www.facebook.com/IoTChain/"
    },
    "overview":"IoT Chain aims to be a A High Security Lite IoT OS",
    "symbol":"ITC",
    "whitepaper":"https://iotchain.io/pdf/ITCWHITEPAPER.pdf",
    "address":"0x5e6b6d9abad9093fdc861ea1600eba1b355cd940",
    "email":"support@iotchain.io"
}