{
  "symbol": "OOP",
  "address": "0x6dfBCB859b4e64a04AFfCE7699a9Ea857c9C1452",
  "overview":{
        "en": "O2##",
        "zh": "我们O2OPLUS是区块链专门企业，努力使区块链技术进一步发展并创造健全、健康的区块链生态系统。,
              目前许多企业都在准备并进行ICO和IEO，然而在没有对业务方向及代币经济进行验证的情况下就策划商业平台，因此经历了很多失败，并导致了 ,
              社会性问题。当前的区块链产业已经告别了单纯依靠白皮书就能得到投资的时期，未来只有结合了在日常生活中直接使用的区块链技术的平台才能够生存。,
              专家们认为，在不远的将来，区块链技术将对很多产业产生影响，并将主导未来成长产业，即第4产业。,
              在种市场下， O2OPLUS超越了线上和线下的界限，正在准备基于SNS的共享经济服务和金融服务。
              在日常生活中，我们所有人都通过许多决定来进行消费。前往卖场之前、移动地点之前、购物之前、吃食物之前、旅行之前、投资之前，我们在 ,
              O2OPLUS与顾客的这些烦恼同在，为了提供最佳服务而正在策划并开发应用了区块链技术、大数据技术、AI技术、LBS技术的平台，并已经开发完 ,
              成适合与个种内容(Dapp)进行联动的主网，以打造区块链生态系统 。
              我们O2OPLUS正在准备2019年可以在4Q内全球电子商务平台和线下卖场中使用的手机电子凭证。,
              我们O2OPLUS将通过全球电子商务市场的流通结构的变化，努力创造能够实现人人共赢的市场环境。
"
  },
  "email": "kjcll1516@gmail.com",
  "website": "https://www.o2oplus.io",
  "whitepaper": "http://www.o2oplus.io/O2OPLUS_PT_CN.pdf",
  "state": "NORMAL",
  "published_on": "2019-10-23",
  "initial_price":{
        "USD":"0.05 USD"
  },
  "links": {
    "blog": "##############",
    "twitter": "##############",
    "telegram": "##############",
    "github": "##############",
    "facebook": "##############",
    "reddit": "##############",
    "slack": "##############",
    "medium": "##############"
  }
}
