  
{
  "symbol": "NEVB",
  "address": "0x88507EA0b9749c8d9716d16F87B3B3eb84cc340e",
  "overview":{This's first virtual currency that applies the concept of blockchain + physical interaction function. The transformation of the traditional Internet team took one year to prepare a perfect New application system of blockchain. While ensuring 100% decentralized operation of blockchain + entities, All physical Bitcoin miner-sharing (smart charging piles for new energy vehicle blocks) will also realize a new mode that the free selection of coin-holders to become mining machine managers.Follow us to promote the conversion of new and old kinetic energy of global vehicles to prevent global warming. Now we sincerely invite you to join us and explore new application fields and methods of blockchain together.}
        "zh": "At the same time, the self-developed SZPW mining coin integrated intelligent algorithm is used for the first time, which means that the charging amount of the mining machine user is converted into the mining machine computing power, and the charging fee is allocated to the mine owner’s income by the same amount. Partners who hold enough NEVB can choose freely Become one of the miners of NEVB"
  },
  "email": "alexisgrayndler4@gmail.com",
  "website": "https://www.nevb.io/",
  "whitepaper": "https://cdn.website-editor.net/908110cbc02046a39d93c1dddf8c4c6c/files/uploaded/NEVB%2520%2520White%2520paper.pdf",
  "state": "NORMAL",
  "published_on": "2018-01-01",
  "initial_price":{
        "ETH":"0 ETH",
        "USD":"0USD",
        "BTC":"0. BTC"
  },
  "links": {
    "blog": "",
    "twitter": "https://twitter.com/NEVB94025478?s=09",
    "telegram": "https://t.me/nevb001",
    "github": "",
    "facebook": "",
    "reddit": "",
    "slack": "",
    "medium": ""
  }
}
