{"symbol": "ATT","address": "0x89Fb927240750c1B15d4743cd58440fc5f14A11C","overview":{"en": "Attila (ATT) is a cryptocurrency and operates on the Ethereum platform. Attila has a current supply of 3,000,000,000 with 450,382,736 in circulation. The last known price of Attila is 0.27811276 USD and is up 19.24 over the last 24 hours. It is currently trading on 5 active market(s) with $343,670.07 traded over the last 24 hours. More information can be found at https://www.attnetwork.org/."},"email": "","website": "https://www.attnetwork.org/","state": "NORMAL","links": {"blog": "","twitter": "https://twitter.com/AChainGalaxy","telegram": "","github": ""}}