{"symbol": "DUCATO","address": "0xa117ea1c0c85CEf648df2b6f40e50bb5475C228d","overview":{"en": "Ducato Protocol Token (DUCATO) is a cryptocurrency and operates on the Ethereum platform. Ducato Protocol Token has a current supply of 50,000,000 with 1,280,000 in circulation. The last known price of Ducato Protocol Token is 16.30459968 USD and is down -2.38 over the last 24 hours. It is currently trading on 5 active market(s) with $242,037.71 traded over the last 24 hours. More information can be found at http://ducato.io/."},"email": "","website": "http://ducato.io/","state": "NORMAL","links": {"blog": "","twitter": "https://twitter.com/DUCATO_DeFi","telegram": "","github": ""}}