{
    "website":"https://ico.snov.io/",
    "published_on":"2017-10-30",
    "links":{
        "telegram":"https://t.me/snovio_ico",
        "reddit":"https://www.reddit.com/user/Snovio_ICO/",
        "facebook":"https://www.facebook.com/Snovio-ICO-147118702534568/",
        "twitter":"https://twitter.com/snovio_ico"
    },
    "overview":"Decentralized lead generation platform.",
    "symbol":"SNOV",
    "initial_price":"0.01 $",
    "whitepaper":"https://tokensale.snov.io/docs/WhitePaperEn.pdf",
    "address":"0xbdc5bac39dbe132b1e030e898ae3830017d7d969",
    "email":"ico@snov.io"
}