{"symbol": "PTU","address": "0xC229c69eB3BB51828D0cAA3509A05a51083898dd","overview":{"en": "Pintu Token (PTU) is an ERC-20 token that is designed to drive and support the long term growth and vision of the Pintu ecosystem and community. The launch of PTU is aimed at rewarding loyal users of the platform and incentivising new members to join Pintu’s expanding ecosystem."},"email": "","website": "https://www.pintu.co.id","state": "NORMAL","links": {"blog": "https://pintu.co.id/blog","twitter": "https://twitter.com/pintuid","telegram": "","github": ""}}