{"symbol": "EAURIC","address": "0xc36C65693eA9e207Ad35d4EE2Fb6c5F6f43BDEC8","overview":{"en": "Eauric (EAURIC) is a cryptocurrency and operates on the Ethereum platform. Eauric has a current supply of 31,650,114 with 27,240,513 in circulation. The last known price of Eauric is 7.46294826 USD and is down -6.03 over the last 24 hours. It is currently trading on 5 active market(s) with $4,341,641.92 traded over the last 24 hours. More information can be found at https://eauric.com/."},"email": "","website": "https://eauric.com/","state": "NORMAL","links": {"blog": "","twitter": "https://twitter.com/eauric4","telegram": "","github": ""}}