{"symbol": "CBK","address": "0xD85a6Ae55a7f33B0ee113C234d2EE308EdeAF7fD","overview":{"en": "Cobak Token (CBK) is a cryptocurrency and operates on the Ethereum platform. Cobak Token has a current supply of 100,000,000 with 2,808,660 in circulation. The last known price of Cobak Token is 6.59485812 USD and is down -8.78 over the last 24 hours. It is currently trading on 6 active market(s) with $19,369,335.70 traded over the last 24 hours. More information can be found at https://cobak.co.kr/."},"email": "","website": "https://cobak.co.kr/","state": "NORMAL","links": {"blog": "https://medium.com/@cobak","twitter": "https://twitter.com/CobakOfficial","telegram": "","github": ""}}