{"symbol": "DEFO","address": "0xe481f2311C774564D517d015e678c2736A25Ddd3","overview":{"en": "DefHold (DEFO) is a cryptocurrency and operates on the Ethereum platform. DefHold has a current supply of 0. The last known price of DefHold is 91.93040597 USD and is down -5.37 over the last 24 hours. It is currently trading on 1 active market(s) with $5,670.43 traded over the last 24 hours. More information can be found at https://defhold.com/."},"email": "","website": "https://defhold.com/","state": "NORMAL","links": {"blog": "https://defhold.medium.com/","twitter": "https://twitter.com/DefHold","telegram": "","github": ""}}