{"symbol": "BDP","address": "0xf3dcbc6D72a4E1892f7917b7C43b74131Df8480e","overview":{"en": "Big Data Protocol (BDP) is a cryptocurrency and operates on the Ethereum platform. Big Data Protocol has a current supply of 32,000,001. The last known price of Big Data Protocol is 2.47560255 USD and is up 3.23 over the last 24 hours. It is currently trading on 7 active market(s) with $8,279,337.03 traded over the last 24 hours. More information can be found at https://bigdataprotocol.com."},"email": "","website": "https://bigdataprotocol.com","state": "NORMAL","links": {"blog": "https://medium.com/big-data-protocol","twitter": "https://twitter.com/bigdataprotocol","telegram": "","github": ""}}