{"symbol": "ZERC","address": "0xf8428A5a99cb452Ea50B6Ea70b052DaA3dF4934F","overview":{"en": "zkRace (formerly DeRace) is both the front-running Web3 horse racing game and the cutting-edge zk-rollup-based infrastructure tailored for GameFi and powered by $ZERC token. zkRace is more than just a game; it’s a paradigm shift in the Web3 gaming space at large."},"email": "","website": "https://www.zkrace.com","state": "NORMAL","links": {"blog": "https://deracenft.medium.com/","twitter": "https://twitter.com/zk_Race","telegram": "","github": ""}}