{

  "symbol": "VTC",

  "address": "0x9073d050Fa90fe910B74E2B1Eb7EFE5A016EAa05",

  "overview":{

        "en":"Verdict block chain ADVERTISING  platform",

        

  },

  "email": "support@verdict.com",

  "website": "http://verdict.co.uk",

  

  "published_on": "2018-06-02",

  "initial_price":{

        "ETH":"0.000001 ETH",

        "USD":"0.0007 USD",

        "BTC":"0.000000067 BTC"

  },

  "links": {

    "twitter": "http:// Twitter.com/verdicttoken",

    "telegram": "https://t.me/verdicttoken"
